invisibleroads_records/__init__.py
invisibleroads_records/constants.py
invisibleroads_records/exceptions.py
invisibleroads_records/models.py
invisibleroads_records/scripts.py
invisibleroads_records/shells.py
invisibleroads_records/tests.py
invisibleroads_records/variables.py
invisibleroads_records/views.py
invisibleroads_records-0.5.9.4.dist-info/METADATA
invisibleroads_records-0.5.9.4.dist-info/WHEEL
invisibleroads_records-0.5.9.4.dist-info/entry_points.txt
invisibleroads_records-0.5.9.4.dist-info/top_level.txt
invisibleroads_records-0.5.9.4.dist-info/zip-safe
invisibleroads_records-0.5.9.4.dist-info/RECORD
