Metadata-Version: 2.1
Name: invisibleroads-records
Version: 0.5.9.4
Summary: Web application database defaults
Home-page: https://github.com/invisibleroads/invisibleroads-records
Author: Roy Hyunjin Han
Author-email: rhh@crosscompute.com
License: UNKNOWN
Keywords: web wsgi bfg pylons pyramid invisibleroads
Platform: UNKNOWN
Classifier: Programming Language :: Python
Classifier: Framework :: Pyramid
Classifier: Topic :: Internet :: WWW/HTTP
Classifier: Topic :: Internet :: WWW/HTTP :: WSGI :: Application
Classifier: License :: OSI Approved :: MIT License
Requires-Dist: invisibleroads (>=0.3.4)
Requires-Dist: invisibleroads-posts (>=0.7.16.3)
Requires-Dist: pyramid
Requires-Dist: pyramid-retry
Requires-Dist: pyramid-tm
Requires-Dist: sqlalchemy
Requires-Dist: transaction
Requires-Dist: zope.sqlalchemy
Requires-Dist: pytest
Requires-Dist: invisibleroads-macros-configuration (>=1.0.8)
Requires-Dist: invisibleroads-macros-log (>=1.0.3)
Requires-Dist: invisibleroads-macros-security (>=1.0.1)
Provides-Extra: test
Requires-Dist: pytest-cov ; extra == 'test'
